{
  "block_id": "block_125",
  "label": "Auto Block 125",
  "category": "Business Plans",
  "description": "Autogenerated block number 125",
  "molt_type": "Instruction",
  "cantocore": "INSTR:AUTO.BLOCK.125; GENERATED=TRUE",
  "tags": [
    "auto",
    "block_125",
    "gen"
  ],
  "snap_config": {
    "snap_to": [
      "Subject"
    ],
    "priority": 5
  },
  "ledger": {
    "originator": "Christopher L Haynes",
    "verified_by": "PoeUMG",
    "created_at": "AUTO",
    "edit_log": [
      {
        "timestamp": "2025-06-29T18:38:54.743453",
        "action": "fill_blocks",
        "user": "Mag",
        "change": "Filled block via Poe in Bolt"
      }
    ]
  },
  "color_code": "yellow"
}