{
  "block_id": "block_565",
  "label": "Auto Block 565",
  "category": "Business Plans",
  "description": "Autogenerated block number 565",
  "molt_type": "Instruction",
  "cantocore": "INSTR:AUTO.BLOCK.565; GENERATED=TRUE",
  "tags": [
    "auto",
    "block_565",
    "gen"
  ],
  "snap_config": {
    "snap_to": [
      "Subject"
    ],
    "priority": 5
  },
  "ledger": {
    "originator": "Christopher L Haynes",
    "verified_by": "PoeUMG",
    "created_at": "AUTO",
    "edit_log": []
  },
  "color_code": "yellow"
}