{
  "block_id": "block_408",
  "label": "Auto Block 408",
  "category": "Business Plans",
  "description": "Autogenerated block number 408",
  "molt_type": "Subject",
  "cantocore": "SUBJE:AUTO.BLOCK.408; GENERATED=TRUE",
  "tags": [
    "auto",
    "block_408",
    "gen"
  ],
  "snap_config": {
    "snap_to": [
      "Instruction"
    ],
    "priority": 8
  },
  "ledger": {
    "originator": "Christopher L Haynes",
    "verified_by": "PoeUMG",
    "created_at": "AUTO",
    "edit_log": [
      {
        "timestamp": "2025-06-29T18:38:56.175749",
        "action": "fill_blocks",
        "user": "Mag",
        "change": "Filled block via Poe in Bolt"
      }
    ]
  },
  "color_code": "green"
}