{
  "block_id": "block_024",
  "label": "Auto Block 24",
  "category": "Business Plans",
  "description": "Autogenerated block number 24",
  "molt_type": "Subject",
  "cantocore": "SUBJE:AUTO.BLOCK.24; GENERATED=TRUE",
  "tags": [
    "auto",
    "block_24",
    "gen"
  ],
  "snap_config": {
    "snap_to": [
      "Instruction"
    ],
    "priority": 4
  },
  "ledger": {
    "originator": "Christopher L Haynes",
    "verified_by": "PoeUMG",
    "created_at": "AUTO",
    "edit_log": [
      {
        "timestamp": "2025-06-29T18:38:55.451350",
        "action": "fill_blocks",
        "user": "Mag",
        "change": "Filled block via Poe in Bolt"
      }
    ]
  },
  "color_code": "green"
}