{
  "block_id": "block_348",
  "label": "Auto Block 348",
  "category": "Business Plans",
  "description": "Autogenerated block number 348",
  "molt_type": "Subject",
  "cantocore": "SUBJE:AUTO.BLOCK.348; GENERATED=TRUE",
  "tags": [
    "auto",
    "block_348",
    "gen"
  ],
  "snap_config": {
    "snap_to": [
      "Instruction"
    ],
    "priority": 8
  },
  "ledger": {
    "originator": "Christopher L Haynes",
    "verified_by": "PoeUMG",
    "created_at": "AUTO",
    "edit_log": []
  },
  "color_code": "green"
}