{
  "block_id": "block_334",
  "label": "Auto Block 334",
  "category": "Business Plans",
  "description": "Autogenerated block number 334",
  "molt_type": "Subject",
  "cantocore": "SUBJE:AUTO.BLOCK.334; GENERATED=TRUE",
  "tags": [
    "auto",
    "block_334",
    "gen"
  ],
  "snap_config": {
    "snap_to": [
      "Instruction"
    ],
    "priority": 4
  },
  "ledger": {
    "originator": "Christopher L Haynes",
    "verified_by": "PoeUMG",
    "created_at": "AUTO",
    "edit_log": [
      {
        "timestamp": "2025-06-29T18:38:56.030454",
        "action": "fill_blocks",
        "user": "Mag",
        "change": "Filled block via Poe in Bolt"
      }
    ]
  },
  "color_code": "green"
}